Fancy_progressbar/__init__.py
Fancy_progressbar/bar.py
Fancy_progressbar/family.py
Fancy_progressbar/handler.py
Fancy_progressbar/options.py
Fancy_progressbar/tokens.py
Fancy_progressbar/utils.py
Fancy_progressbar-2.0.2.dist-info/LICENSE.txt
Fancy_progressbar-2.0.2.dist-info/METADATA
Fancy_progressbar-2.0.2.dist-info/WHEEL
Fancy_progressbar-2.0.2.dist-info/top_level.txt
Fancy_progressbar-2.0.2.dist-info/RECORD
