Metadata-Version: 2.1
Name: Fancy-progressbar
Version: 2.0.2
Summary: An easy to use multi progressbar manager
Home-page: https://github.com/Plawn/Fancy_progressbar
Author: Plawn
Author-email: plawn.yay@gmail.com
License: apache-2.0
Platform: UNKNOWN
